MANIFEST.in
pyrx.py
readme.md
setup.py
PyRx.egg-info/PKG-INFO
PyRx.egg-info/SOURCES.txt
PyRx.egg-info/dependency_links.txt
PyRx.egg-info/top_level.txt
test/test_pyrx.py