Metadata-Version: 1.0
Name: PyRx
Version: 0.3.0
Summary: Rx schema and validation system
Home-page: https://github.com/uniphil/pyrx
Author: UNKNOWN
Author-email: UNKNOWN
License: GPLv2
Platform: UNKNOWN
